
{
  "Items": [
    {
      "proto_id": 0,
      "name": "Cursed Wind Card",
      "min_level": 20,
      "type": "PASSIVE",
      "element": "WIND",

      "stats": {
        "swordAttack": 1,
        "magicAttack": 10,
        "moveSpeed": 1
      }
    },
    {
      "proto_id": 1,
      "name": "Ice Card",
      "min_level": 2,
      "type": "PASSIVE",
      "element": "ICE",

      "stats": {
        "swordAttack": 5,
        "magicAttack": 5,
        "moveSpeed": 2
      }
    },
    {
      "proto_id": 2,
      "name": "Fire Card",
      "min_level": 4,
      "type": "SPELL",
      "element": "FIRE",

      "stats": {
        "swordAttack": 5,
        "magicAttack": 5,
        "moveSpeed": 1
      }
    },
    {
      "proto_id": 3,
      "name": "Wind Card",
      "min_level": 5,
      "type": "SPELL",
      "element": "WIND",

      "stats": {
        "swordAttack": 5,
        "magicAttack": 5,
        "moveSpeed": 2
      }
    },

    {
      "proto_id": 4,
      "name": "Magic Fire Card",
      "min_level": 10,
      "type": "SPELL",
      "element": "FIRE"
    },

    {
      "proto_id": 5,
      "name": "Magic Ice Card",
      "min_level": 10,
      "type": "SPELL",
      "element": "ICE"
    },

    {
      "proto_id": 6,
      "name": "Magic Wind Card",
      "min_level": 10,
      "type": "PASSIVE",
      "element": "Wind",

      "stats": {
        "maxHp": 10,
        "defence": 5
      }
    }
  ]
}